{
  "project_info": {
    "project_number": "527356459689",
    "project_id": "wibashapp",
    "storage_bucket": "wibashapp.appspot.com"
  },
  "client": [
    {
      "client_info": {
        "mobilesdk_app_id": "1:527356459689:android:dd03770811c4a3868a07b8",
        "android_client_info": {
          "package_name": "com.wibash.wibashapp"
        }
      },
      "oauth_client": [
        {
          "client_id": "527356459689-7agncaimdt73374b54bgmq65npj4v8qa.apps.googleusercontent.com",
          "client_type": 3
        }
      ],
      "api_key": [
        {
          "current_key": "AIzaSyB1EWK5rm38HxNP-I_qWTJ40BaVUF0cD4k"
        }
      ],
      "services": {
        "appinvite_service": {
          "other_platform_oauth_client": [
            {
              "client_id": "527356459689-7agncaimdt73374b54bgmq65npj4v8qa.apps.googleusercontent.com",
              "client_type": 3
            }
          ]
        }
      }
    }
  ],
  "configuration_version": "1"
}